n6py/__init__.py
n6py/app/__init__.py
n6py/app/git_app.py
n6py/display/__init__.py
n6py/display/box.py
n6py/display/html.py
n6py/encode/__init__.py
n6py/encode/split.py
n6py/encode/split_most_common.py
n6py/stats/__init__.py
n6py/stats/n_changed.py
n6py-0.1.31.dist-info/METADATA
n6py-0.1.31.dist-info/WHEEL
n6py-0.1.31.dist-info/LICENSE
n6py-0.1.31.dist-info/RECORD
