Metadata-Version: 2.1
Name: n6py
Version: 0.1.31
Summary: Python Power Tools for Scientific Computing, Machine Learning and Deep Learning.
Home-page: https://py.n6.ai
License: MIT
Keywords: n6py,ai,artificial intelligence,dl,deep learning,ml,machine learning,jupyter,notebook
Author: Sergej Samsonenko
Author-email: contact@sergej.codes
Requires-Python: >=3.8,<4.0
Classifier: Development Status :: 1 - Planning
Classifier: Framework :: Jupyter
Classifier: Intended Audience :: Developers
Classifier: Intended Audience :: Science/Research
Classifier: License :: OSI Approved :: MIT License
Classifier: Operating System :: MacOS
Classifier: Operating System :: Microsoft :: Windows
Classifier: Operating System :: POSIX
Classifier: Operating System :: Unix
Classifier: Programming Language :: Python
Classifier: Programming Language :: Python :: 3
Classifier: Programming Language :: Python :: 3.8
Classifier: Programming Language :: Python :: 3.9
Classifier: Programming Language :: Python :: 3.10
Classifier: Programming Language :: Python :: 3.11
Classifier: Topic :: Scientific/Engineering
Classifier: Topic :: Scientific/Engineering :: Artificial Intelligence
Classifier: Topic :: Software Development
Classifier: Topic :: Software Development :: Libraries
Classifier: Topic :: Software Development :: Libraries :: Python Modules
Requires-Dist: ipython (>=8.7.0,<9.0.0)
Requires-Dist: numpy (>=1.24.1,<2.0.0)
Requires-Dist: pandas (>=1.5.2,<2.0.0)
Project-URL: Bug Tracker, https://github.com/n6ai/n6py/issues
Project-URL: Documentation, https://py.n6.ai
Project-URL: Repository, https://github.com/n6ai/n6py
